sphinxcontrib/lookup_yaml/__init__.py
sphinxcontrib_lookup_yaml-0.0.1.dist-info/LICENSE.txt
sphinxcontrib_lookup_yaml-0.0.1.dist-info/METADATA
sphinxcontrib_lookup_yaml-0.0.1.dist-info/RECORD
sphinxcontrib_lookup_yaml-0.0.1.dist-info/WHEEL
sphinxcontrib_lookup_yaml-0.0.1.dist-info/top_level.txt
